Lab1/vending_machine/change_state.v
`include "vending_machine_def.v"


module change_state(clk,reset_n,current_total_nxt,current_total);

	input clk;
	input reset_n;
	input [`kTotalBits-1:0] current_total_nxt;
	output reg [`kTotalBits-1:0] current_total;
	
	// Sequential logic
	always @(posedge clk ) begin
		if (!reset_n) begin
			// TODO: reset all states.
			current_total<=0;
		end
		else begin
			// TODO: update all states.
			current_total<=current_total_nxt;

		end
	end
endmodule

Lab1/vending_machine/calculate_current_state.v
`include "vending_machine_def.v"
	

module calculate_current_state(i_input_coin,i_select_item,item_price,coin_value,current_total,
input_total, output_total, return_total,current_total_nxt, wait_time,o_available_item,o_output_item,i_trigger_return);

	input [`kNumCoins-1:0] i_input_coin;
	input [`kNumItems-1:0]	i_select_item;			
	input [31:0] item_price [`kNumItems-1:0];
	input [31:0] coin_value [`kNumCoins-1:0];	
	input [`kTotalBits-1:0] current_total;
	input [31:0] wait_time;
	output reg [`kNumItems-1:0] o_available_item,o_output_item;
	output reg  [`kTotalBits-1:0] input_total, output_total, return_total, current_total_nxt;
	integer i;
	integer j;

	input i_trigger_return;

	// Combinational logic
	always @(*) begin
		// Initialize variables
		input_total = 0;
		current_total_nxt = current_total;
		return_total = 0;
		output_total = 0;

		for (j = 0; j < `kNumItems; j = j + 1) begin
            o_output_item[j] = 0;
            o_available_item[j] = 0;
        end

		for (i = 0; i < `kNumCoins; i = i + 1) begin
			if (i_input_coin[i]) input_total = input_total + coin_value[i];
		end
		current_total_nxt = current_total_nxt + input_total;

		for (i = 0; i < `kNumItems; i = i + 1) begin
			if (i_select_item[i] && (current_total_nxt >= item_price[i])) begin
				current_total_nxt = current_total_nxt - item_price[i];
				o_output_item[i] = 1;
			end 
			else begin
				o_output_item[i] = 0;
			end
		end

		if (i_trigger_return || wait_time <= 0) begin
			return_total = current_total_nxt;
			current_total_nxt = 0;
		end
	end

	always @(*) begin
		for (i = 0; i < `kNumItems; i = i + 1) begin
			if (current_total_nxt >= item_price[i]) begin
				o_available_item[i] = 1;
			end
			else begin
				o_available_item[i] = 0;
			end
		end
	end
	

 
endmodule

Lab1/vending_machine/check_time_and_coin.v
`include "vending_machine_def.v"


module check_time_and_coin(i_trigger_return, current_total, i_input_coin,i_select_item,clk,reset_n,wait_time,o_return_coin);
	input clk;
	input reset_n;
	input i_trigger_return;
	input [31:0] current_total;
	input [`kNumCoins-1:0] i_input_coin;
	input [`kNumItems-1:0]	i_select_item;
	output reg  [`kNumCoins-1:0] o_return_coin;
	output reg [31:0] wait_time;

	// initiate values
	initial begin
		// TODO: initiate values
		o_return_coin=0;
		wait_time=`kWaitTime;			
	end
	
	always @(*) begin
		o_return_coin = 3'b000;
		// TODO: o_return_coin
		if(i_trigger_return || wait_time <= 0) begin
			o_return_coin = 3'b001;
			if(current_total >= 1000) begin
				o_return_coin = 3'b101;
			end
			else if(current_total >= 500) begin
				o_return_coin = 3'b011;
			end
		end
	end

	always @(posedge clk) begin
		if (!reset_n) begin
			// Synchronous reset logic
			wait_time <= `kWaitTime;
		end else begin
			if (|i_select_item || |i_input_coin) begin
				wait_time <= `kWaitTime;
			end else begin
				// Decrement wait_time
				if (wait_time > 0) begin
					wait_time <= wait_time - 1;
				end
				else begin
					wait_time <= 0;
				end
			end
		end
	end
endmodule

Lab1/vending_machine/vending_machine.v
// Title         : vending_machine.v
// Author      : Jae-Eon Jo (Jojaeeon@postech.ac.kr) 
//			     Dongup Kwon (nankdu7@postech.ac.kr) (2015.03.30)
//			     Jaehun Ryu (jaehunryu@postech.ac.kr) (2021.03.07)

`include "vending_machine_def.v"


module vending_machine (
	clk,							// Clock signal
	reset_n,						// Reset signal (active-low)

	i_input_coin,				// coin is inserted.
	i_select_item,				// item is selected.
	i_trigger_return,			// change-return is triggered 

	o_available_item,			// Sign of the item availability
	o_output_item,			// Sign of the item withdrawal
	o_return_coin				// Sign of the coin return
);

	// Ports Declaration
	// Do not modify the module interface
	input clk;
	input reset_n;
	
	input [`kNumCoins-1:0] i_input_coin;
	input [`kNumItems-1:0] i_select_item;
	input i_trigger_return;
		
	output [`kNumItems-1:0] o_available_item;
	output [`kNumItems-1:0] o_output_item;
	output [`kNumCoins-1:0] o_return_coin;


	

	// Do not modify the values.
	wire [31:0] item_price [`kNumItems-1:0];	// Price of each item
	wire [31:0] coin_value [`kNumCoins-1:0];	// Value of each coin
	assign item_price[0] = 400;
	assign item_price[1] = 500;
	assign item_price[2] = 1000;
	assign item_price[3] = 2000;
	assign coin_value[0] = 100;
	assign coin_value[1] = 500;
	assign coin_value[2] = 1000;

	// Internal states. You may add your own net variables.
	wire [`kTotalBits-1:0] current_total;
	
	// Next internal states. You may add your own net variables.
	wire [`kTotalBits-1:0] current_total_nxt;

	
	// Variables. You may add more your own net variables.
	
	wire [`kTotalBits-1:0] input_total;
	wire [`kTotalBits-1:0] output_total, return_total;
	wire [31:0] wait_time;
	//maybe variables to store information about state information such as initial state, insert coin state, dispense item state, return coin state
	


	

	//to solve the Signal is not used: error for _total values
	reg [31:0]counter1;
	reg [31:0]counter2;
	always @(posedge clk) begin
		counter1<=input_total;
		counter2<=output_total;
		counter1<=return_total;
		counter1<=counter2;
		counter2<=counter1;
	end


	// This module interface, structure, and given a number of modules are not mandatory but recommended.
	// However, Implementations that use modules are mandatory.
		
  	check_time_and_coin check_time_and_coin_module(.i_input_coin(i_input_coin),
  									.i_select_item(i_select_item),
									.clk(clk),
									.i_trigger_return(i_trigger_return),
									.current_total(current_total),
									.reset_n(reset_n),
									.wait_time(wait_time),
									.o_return_coin(o_return_coin));

	calculate_current_state calculate_current_state_module(.i_input_coin(i_input_coin),
										.i_select_item(i_select_item),
										.item_price(item_price),
										.coin_value(coin_value),
										.current_total(current_total),
										.input_total(input_total),
										.output_total(output_total),
										.return_total(return_total),
										.current_total_nxt(current_total_nxt),
										.wait_time(wait_time),
										.o_available_item(o_available_item),
										.o_output_item(o_output_item),
										
										.i_trigger_return(i_trigger_return)
										);
	
  	change_state change_state_module(
						.clk(clk),
						.reset_n(reset_n),
						.current_total_nxt(current_total_nxt),
						.current_total(current_total));


endmodule

Lab1/vending_machine/waveform.vcd
$version Generated by VerilatedVcd $end
$timescale 1ps $end
 $scope module TOP $end
  $var wire 1 / clk $end
  $var wire 1 0 reset_n $end
  $var wire 3 1 i_input_coin [2:0] $end
  $var wire 4 2 i_select_item [3:0] $end
  $var wire 1 3 i_trigger_return $end
  $var wire 4 4 o_available_item [3:0] $end
  $var wire 4 5 o_output_item [3:0] $end
  $var wire 3 6 o_return_coin [2:0] $end
  $scope module vending_machine $end
   $var wire 1 / clk $end
   $var wire 1 0 reset_n $end
   $var wire 3 1 i_input_coin [2:0] $end
   $var wire 4 2 i_select_item [3:0] $end
   $var wire 1 3 i_trigger_return $end
   $var wire 4 4 o_available_item [3:0] $end
   $var wire 4 5 o_output_item [3:0] $end
   $var wire 3 6 o_return_coin [2:0] $end
   $var wire 32 # item_price[0] [31:0] $end
   $var wire 32 $ item_price[1] [31:0] $end
   $var wire 32 % item_price[2] [31:0] $end
   $var wire 32 & item_price[3] [31:0] $end
   $var wire 32 ' coin_value[0] [31:0] $end
   $var wire 32 ( coin_value[1] [31:0] $end
   $var wire 32 ) coin_value[2] [31:0] $end
   $var wire 32 + current_total [31:0] $end
   $var wire 32 7 current_total_nxt [31:0] $end
   $var wire 32 8 input_total [31:0] $end
   $var wire 32 : output_total [31:0] $end
   $var wire 32 9 return_total [31:0] $end
   $var wire 32 , wait_time [31:0] $end
   $var wire 32 - counter1 [31:0] $end
   $var wire 32 . counter2 [31:0] $end
   $scope module calculate_current_state_module $end
    $var wire 3 1 i_input_coin [2:0] $end
    $var wire 4 2 i_select_item [3:0] $end
    $var wire 32 # item_price[0] [31:0] $end
    $var wire 32 $ item_price[1] [31:0] $end
    $var wire 32 % item_price[2] [31:0] $end
    $var wire 32 & item_price[3] [31:0] $end
    $var wire 32 ' coin_value[0] [31:0] $end
    $var wire 32 ( coin_value[1] [31:0] $end
    $var wire 32 ) coin_value[2] [31:0] $end
    $var wire 32 + current_total [31:0] $end
    $var wire 32 , wait_time [31:0] $end
    $var wire 4 4 o_available_item [3:0] $end
    $var wire 4 5 o_output_item [3:0] $end
    $var wire 32 8 input_total [31:0] $end
    $var wire 32 : output_total [31:0] $end
    $var wire 32 9 return_total [31:0] $end
    $var wire 32 7 current_total_nxt [31:0] $end
    $var wire 32 * i [31:0] $end
    $var wire 32 ; j [31:0] $end
    $var wire 1 3 i_trigger_return $end
   $upscope $end
   $scope module change_state_module $end
    $var wire 1 / clk $end
    $var wire 1 0 reset_n $end
    $var wire 32 7 current_total_nxt [31:0] $end
    $var wire 32 + current_total [31:0] $end
   $upscope $end
   $scope module check_time_and_coin_module $end
    $var wire 1 / clk $end
    $var wire 1 0 reset_n $end
    $var wire 1 3 i_trigger_return $end
    $var wire 32 + current_total [31:0] $end
    $var wire 3 1 i_input_coin [2:0] $end
    $var wire 4 2 i_select_item [3:0] $end
    $var wire 3 6 o_return_coin [2:0] $end
    $var wire 32 , wait_time [31:0] $end
   $upscope $end
  $upscope $end
 $upscope $end
$enddefinitions $end


#0
b00000000000000000000000110010000 #
b00000000000000000000000111110100 $
b00000000000000000000001111101000 %
b00000000000000000000011111010000 &
b00000000000000000000000001100100 '
b00000000000000000000000111110100 (
b00000000000000000000001111101000 )
b00000000000000000000000000000100 *
b01110011010110000001011000110101 +
b00000000000000000000000000001010 ,
b00000110101011011111010100111011 -
b11000110011011010100110101011000 .
1/
10
b000 1
b0000 2
03
b1111 4
b0000 5
b000 6
b01110011010110000001011000110101 7
b00000000000000000000000000000000 8
b00000000000000000000000000000000 9
b00000000000000000000000000000000 :
b00000000000000000000000000000100 ;
#1
0/
#2
b00000000000000000000000000000000 +
b11000110011011010100110101011000 -
b00000110101011011111010100111011 .
1/
00
b0000 4
b00000000000000000000000000000000 7
#3
0/
#4
b00000110101011011111010100111011 -
b11000110011011010100110101011000 .
1/
#5
0/
#6
b00000000000000000000000000001001 ,
b11000110011011010100110101011000 -
b00000110101011011111010100111011 .
1/
10
#7
0/
#8
b00000000000000000000000001100100 +
b00000000000000000000000000001010 ,
b00000110101011011111010100111011 -
b11000110011011010100110101011000 .
1/
b001 1
b00000000000000000000000011001000 7
b00000000000000000000000001100100 8
#9
0/
#10
b00000000000000000000000000001001 ,
b11000110011011010100110101011000 -
b00000110101011011111010100111011 .
1/
b000 1
b00000000000000000000000001100100 7
b00000000000000000000000000000000 8
#11
0/
#12
b00000000000000000000000011001000 +
b00000000000000000000000000001010 ,
b00000110101011011111010100111011 -
b11000110011011010100110101011000 .
1/
b001 1
b00000000000000000000000100101100 7
b00000000000000000000000001100100 8
#13
0/
#14
b00000000000000000000000000001001 ,
b11000110011011010100110101011000 -
b00000110101011011111010100111011 .
1/
b000 1
b00000000000000000000000011001000 7
b00000000000000000000000000000000 8
#15
0/
#16
b00000000000000000000000100101100 +
b00000000000000000000000000001010 ,
b00000110101011011111010100111011 -
b11000110011011010100110101011000 .
1/
b001 1
b00000000000000000000000110010000 7
b00000000000000000000000001100100 8
#17
0/
#18
b00000000000000000000000000001001 ,
b11000110011011010100110101011000 -
b00000110101011011111010100111011 .
1/
b000 1
b00000000000000000000000100101100 7
b00000000000000000000000000000000 8
#19
0/
#20
b00000000000000000000000110010000 +
b00000000000000000000000000001010 ,
b00000110101011011111010100111011 -
b11000110011011010100110101011000 .
1/
b001 1
b0001 4
b00000000000000000000000111110100 7
b00000000000000000000000001100100 8
#21
0/
#22
b00000000000000000000000000001001 ,
b11000110011011010100110101011000 -
b00000110101011011111010100111011 .
1/
b000 1
b00000000000000000000000110010000 7
b00000000000000000000000000000000 8
#23
0/
#24
b00000000000000000000000111110100 +
b00000000000000000000000000001010 ,
b00000110101011011111010100111011 -
b11000110011011010100110101011000 .
1/
b001 1
b0011 4
b00000000000000000000001001011000 7
b00000000000000000000000001100100 8
#25
0/
#26
b00000000000000000000000000001001 ,
b11000110011011010100110101011000 -
b00000110101011011111010100111011 .
1/
b000 1
b00000000000000000000000111110100 7
b00000000000000000000000000000000 8
#27
0/
#28
b00000000000000000000000000001000 ,
b00000110101011011111010100111011 -
b11000110011011010100110101011000 .
1/
#29
0/
#30
b00000000000000000000000000000000 +
b00000000000000000000000000001010 ,
b11000110011011010100110101011000 -
b00000110101011011111010100111011 .
1/
00
b0000 4
b00000000000000000000000000000000 7
#31
0/
#32
b00000110101011011111010100111011 -
b11000110011011010100110101011000 .
1/
#33
0/
#34
b00000000000000000000000000001001 ,
b11000110011011010100110101011000 -
b00000110101011011111010100111011 .
1/
10
#35
0/
#36
b00000000000000000000000111110100 +
b00000000000000000000000000001010 ,
b00000110101011011111010100111011 -
b11000110011011010100110101011000 .
1/
b010 1
b0011 4
b00000000000000000000001111101000 7
b00000000000000000000000111110100 8
#37
0/
#38
b00000000000000000000000000001001 ,
b11000110011011010100110101011000 -
b00000110101011011111010100111011 .
1/
b000 1
b00000000000000000000000111110100 7
b00000000000000000000000000000000 8
#39
0/
#40
b00000000000000000000001111101000 +
b00000000000000000000000000001010 ,
b00000110101011011111010100111011 -
b11000110011011010100110101011000 .
1/
b010 1
b0111 4
b00000000000000000000010111011100 7
b00000000000000000000000111110100 8
#41
0/
#42
b00000000000000000000000000001001 ,
b11000110011011010100110101011000 -
b00000110101011011111010100111011 .
1/
b000 1
b00000000000000000000001111101000 7
b00000000000000000000000000000000 8
#43
0/
#44
b00000000000000000000010111011100 +
b00000000000000000000000000001010 ,
b00000110101011011111010100111011 -
b11000110011011010100110101011000 .
1/
b010 1
b00000000000000000000011111010000 7
b00000000000000000000000111110100 8
#45
0/
#46
b00000000000000000000000000001001 ,
b11000110011011010100110101011000 -
b00000110101011011111010100111011 .
1/
b000 1
b00000000000000000000010111011100 7
b00000000000000000000000000000000 8
#47
0/
#48
b00000000000000000000011111010000 +
b00000000000000000000000000001010 ,
b00000110101011011111010100111011 -
b11000110011011010100110101011000 .
1/
b010 1
b1111 4
b00000000000000000000100111000100 7
b00000000000000000000000111110100 8
#49
0/
#50
b00000000000000000000000000001001 ,
b11000110011011010100110101011000 -
b00000110101011011111010100111011 .
1/
b000 1
b00000000000000000000011111010000 7
b00000000000000000000000000000000 8
#51
0/
#52
b00000000000000000000000000001000 ,
b00000110101011011111010100111011 -
b11000110011011010100110101011000 .
1/
#53
0/
#54
b00000000000000000000000000000000 +
b00000000000000000000000000001010 ,
b11000110011011010100110101011000 -
b00000110101011011111010100111011 .
1/
00
b0000 4
b00000000000000000000000000000000 7
#55
0/
#56
b00000110101011011111010100111011 -
b11000110011011010100110101011000 .
1/
#57
0/
#58
b00000000000000000000000000001001 ,
b11000110011011010100110101011000 -
b00000110101011011111010100111011 .
1/
10
#59
0/
#60
b00000000000000000000001111101000 +
b00000000000000000000000000001010 ,
b00000110101011011111010100111011 -
b11000110011011010100110101011000 .
1/
b100 1
b0111 4
b00000000000000000000011111010000 7
b00000000000000000000001111101000 8
#61
0/
#62
b00000000000000000000000000001001 ,
b11000110011011010100110101011000 -
b00000110101011011111010100111011 .
1/
b000 1
b00000000000000000000001111101000 7
b00000000000000000000000000000000 8
#63
0/
#64
b00000000000000000000011111010000 +
b00000000000000000000000000001010 ,
b00000110101011011111010100111011 -
b11000110011011010100110101011000 .
1/
b100 1
b1111 4
b00000000000000000000101110111000 7
b00000000000000000000001111101000 8
#65
0/
#66
b00000000000000000000000000001001 ,
b11000110011011010100110101011000 -
b00000110101011011111010100111011 .
1/
b000 1
b00000000000000000000011111010000 7
b00000000000000000000000000000000 8
#67
0/
#68
b00000000000000000000000000001000 ,
b00000110101011011111010100111011 -
b11000110011011010100110101011000 .
1/
#69
0/
#70
b00000000000000000000000000000000 +
b00000000000000000000000000001010 ,
b11000110011011010100110101011000 -
b00000110101011011111010100111011 .
1/
00
b0000 4
b00000000000000000000000000000000 7
#71
0/
#72
b00000110101011011111010100111011 -
b11000110011011010100110101011000 .
1/
#73
0/
#74
b00000000000000000000000000001001 ,
b11000110011011010100110101011000 -
b00000110101011011111010100111011 .
1/
10
#75
0/
#76
b00000000000000000000001111101000 +
b00000000000000000000000000001010 ,
b00000110101011011111010100111011 -
b11000110011011010100110101011000 .
1/
b100 1
b0111 4
b00000000000000000000011111010000 7
b00000000000000000000001111101000 8
#77
0/
#78
b00000000000000000000000000001001 ,
b11000110011011010100110101011000 -
b00000110101011011111010100111011 .
1/
b000 1
b00000000000000000000001111101000 7
b00000000000000000000000000000000 8
#79
0/
#80
b00000000000000000000011111010000 +
b00000000000000000000000000001010 ,
b00000110101011011111010100111011 -
b11000110011011010100110101011000 .
1/
b100 1
b1111 4
b00000000000000000000101110111000 7
b00000000000000000000001111101000 8
#81
0/
#82
b00000000000000000000000000001001 ,
b11000110011011010100110101011000 -
b00000110101011011111010100111011 .
1/
b000 1
b00000000000000000000011111010000 7
b00000000000000000000000000000000 8
#83
0/
#84
b00000000000000000000101110111000 +
b00000000000000000000000000001010 ,
b00000110101011011111010100111011 -
b11000110011011010100110101011000 .
1/
b100 1
b00000000000000000000111110100000 7
b00000000000000000000001111101000 8
#85
0/
#86
b00000000000000000000000000001001 ,
b11000110011011010100110101011000 -
b00000110101011011111010100111011 .
1/
b000 1
b00000000000000000000101110111000 7
b00000000000000000000000000000000 8
#87
0/
#88
b00000000000000000000101000101000 +
b00000000000000000000000000001010 ,
b00000110101011011111010100111011 -
b11000110011011010100110101011000 .
1/
b0001 2
b0001 5
b00000000000000000000100010011000 7
#89
0/
#90
b00000000000000000000000000001001 ,
b11000110011011010100110101011000 -
b00000110101011011111010100111011 .
1/
b0000 2
b0000 5
b00000000000000000000101000101000 7
#91
0/
#92
b00000000000000000000000000001000 ,
b00000110101011011111010100111011 -
b11000110011011010100110101011000 .
1/
#93
0/
#94
b00000000000000000000000000000111 ,
b11000110011011010100110101011000 -
b00000110101011011111010100111011 .
1/
#95
0/
#96
b00000000000000000000100010011000 +
b00000000000000000000000000001010 ,
b00000110101011011111010100111011 -
b11000110011011010100110101011000 .
1/
b0001 2
b0001 5
b00000000000000000000011100001000 7
#97
0/
#98
b00000000000000000000000000001001 ,
b11000110011011010100110101011000 -
b00000110101011011111010100111011 .
1/
b0000 2
b0000 5
b00000000000000000000100010011000 7
#99
0/
#100
b00000000000000000000000000001000 ,
b00000110101011011111010100111011 -
b11000110011011010100110101011000 .
1/
#101
0/
#102
b00000000000000000000000000000111 ,
b11000110011011010100110101011000 -
b00000110101011011111010100111011 .
1/
#103
0/
#104
b00000000000000000000011100001000 +
b00000000000000000000000000001010 ,
b00000110101011011111010100111011 -
b11000110011011010100110101011000 .
1/
b0001 2
b0111 4
b0001 5
b00000000000000000000010101111000 7
#105
0/
#106
b00000000000000000000000000001001 ,
b11000110011011010100110101011000 -
b00000110101011011111010100111011 .
1/
b0000 2
b0000 5
b00000000000000000000011100001000 7
#107
0/
#108
b00000000000000000000000000001000 ,
b00000110101011011111010100111011 -
b11000110011011010100110101011000 .
1/
#109
0/
#110
b00000000000000000000000000000111 ,
b11000110011011010100110101011000 -
b00000110101011011111010100111011 .
1/
#111
0/
#112
b00000000000000000000010101111000 +
b00000000000000000000000000001010 ,
b00000110101011011111010100111011 -
b11000110011011010100110101011000 .
1/
b0001 2
b0001 5
b00000000000000000000001111101000 7
#113
0/
#114
b00000000000000000000000000001001 ,
b11000110011011010100110101011000 -
b00000110101011011111010100111011 .
1/
b0000 2
b0000 5
b00000000000000000000010101111000 7
#115
0/
#116
b00000000000000000000000000001000 ,
b00000110101011011111010100111011 -
b11000110011011010100110101011000 .
1/
#117
0/
#118
b00000000000000000000000000000111 ,
b11000110011011010100110101011000 -
b00000110101011011111010100111011 .
1/
#119
0/
#120
b00000000000000000000001111101000 +
b00000000000000000000000000001010 ,
b00000110101011011111010100111011 -
b11000110011011010100110101011000 .
1/
b0001 2
b0001 5
b00000000000000000000001001011000 7
#121
0/
#122
b00000000000000000000000000001001 ,
b11000110011011010100110101011000 -
b00000110101011011111010100111011 .
1/
b0000 2
b0000 5
b00000000000000000000001111101000 7
#123
0/
#124
b00000000000000000000000000001000 ,
b00000110101011011111010100111011 -
b11000110011011010100110101011000 .
1/
#125
0/
#126
b00000000000000000000000000000111 ,
b11000110011011010100110101011000 -
b00000110101011011111010100111011 .
1/
#127
0/
#128
b00000000000000000000001001011000 +
b00000000000000000000000000001010 ,
b00000110101011011111010100111011 -
b11000110011011010100110101011000 .
1/
b0001 2
b0011 4
b0001 5
b00000000000000000000000011001000 7
#129
0/
#130
b00000000000000000000000000001001 ,
b11000110011011010100110101011000 -
b00000110101011011111010100111011 .
1/
b0000 2
b0000 5
b00000000000000000000001001011000 7
#131
0/
#132
b00000000000000000000000000001000 ,
b00000110101011011111010100111011 -
b11000110011011010100110101011000 .
1/
#133
0/
#134
b00000000000000000000000000000111 ,
b11000110011011010100110101011000 -
b00000110101011011111010100111011 .
1/
#135
0/
#136
b00000000000000000000000011001000 +
b00000000000000000000000000001010 ,
b00000110101011011111010100111011 -
b11000110011011010100110101011000 .
1/
b0001 2
b0000 4
b00000000000000000000000011001000 7
#137
0/
#138
b00000000000000000000000000001001 ,
b11000110011011010100110101011000 -
b00000110101011011111010100111011 .
1/
b0000 2
#139
0/
#140
b00000000000000000000000000001000 ,
b00000110101011011111010100111011 -
b11000110011011010100110101011000 .
1/
#141
0/
#142
b00000000000000000000000000000111 ,
b11000110011011010100110101011000 -
b00000110101011011111010100111011 .
1/
#143
0/
#144
b00000000000000000000000000000110 ,
b00000110101011011111010100111011 -
b11000110011011010100110101011000 .
1/
#145
0/
#146
b00000000000000000000000000000101 ,
b11000110011011010100110101011000 -
b00000110101011011111010100111011 .
1/
#147
0/
#148
b00000000000000000000010010110000 +
b00000000000000000000000000001010 ,
b00000110101011011111010100111011 -
b11000110011011010100110101011000 .
1/
b100 1
b0111 4
b00000000000000000000100010011000 7
b00000000000000000000001111101000 8
#149
0/
#150
b00000000000000000000000000001001 ,
b11000110011011010100110101011000 -
b00000110101011011111010100111011 .
1/
b000 1
b00000000000000000000010010110000 7
b00000000000000000000000000000000 8
#151
0/
#152
b00000000000000000000100010011000 +
b00000000000000000000000000001010 ,
b00000110101011011111010100111011 -
b11000110011011010100110101011000 .
1/
b100 1
b1111 4
b00000000000000000000110010000000 7
b00000000000000000000001111101000 8
#153
0/
#154
b00000000000000000000000000001001 ,
b11000110011011010100110101011000 -
b00000110101011011111010100111011 .
1/
b000 1
b00000000000000000000100010011000 7
b00000000000000000000000000000000 8
#155
0/
#156
b00000000000000000000110010000000 +
b00000000000000000000000000001010 ,
b00000110101011011111010100111011 -
b11000110011011010100110101011000 .
1/
b100 1
b00000000000000000001000001101000 7
b00000000000000000000001111101000 8
#157
0/
#158
b00000000000000000000000000001001 ,
b11000110011011010100110101011000 -
b00000110101011011111010100111011 .
1/
b000 1
b00000000000000000000110010000000 7
b00000000000000000000000000000000 8
#159
0/
#160
b00000000000000000000101010001100 +
b00000000000000000000000000001010 ,
b00000110101011011111010100111011 -
b11000110011011010100110101011000 .
1/
b0010 2
b0010 5
b00000000000000000000100010011000 7
#161
0/
#162
b00000000000000000000000000001001 ,
b11000110011011010100110101011000 -
b00000110101011011111010100111011 .
1/
b0000 2
b0000 5
b00000000000000000000101010001100 7
#163
0/
#164
b00000000000000000000000000001000 ,
b00000110101011011111010100111011 -
b11000110011011010100110101011000 .
1/
#165
0/
#166
b00000000000000000000000000000111 ,
b11000110011011010100110101011000 -
b00000110101011011111010100111011 .
1/
#167
0/
#168
b00000000000000000000100010011000 +
b00000000000000000000000000001010 ,
b00000110101011011111010100111011 -
b11000110011011010100110101011000 .
1/
b0010 2
b0010 5
b00000000000000000000011010100100 7
#169
0/
#170
b00000000000000000000000000001001 ,
b11000110011011010100110101011000 -
b00000110101011011111010100111011 .
1/
b0000 2
b0000 5
b00000000000000000000100010011000 7
#171
0/
#172
b00000000000000000000000000001000 ,
b00000110101011011111010100111011 -
b11000110011011010100110101011000 .
1/
#173
0/
#174
b00000000000000000000000000000111 ,
b11000110011011010100110101011000 -
b00000110101011011111010100111011 .
1/
#175
0/
#176
b00000000000000000000011010100100 +
b00000000000000000000000000001010 ,
b00000110101011011111010100111011 -
b11000110011011010100110101011000 .
1/
b0010 2
b0111 4
b0010 5
b00000000000000000000010010110000 7
#177
0/
#178
b00000000000000000000000000001001 ,
b11000110011011010100110101011000 -
b00000110101011011111010100111011 .
1/
b0000 2
b0000 5
b00000000000000000000011010100100 7
#179
0/
#180
b00000000000000000000000000001000 ,
b00000110101011011111010100111011 -
b11000110011011010100110101011000 .
1/
#181
0/
#182
b00000000000000000000000000000111 ,
b11000110011011010100110101011000 -
b00000110101011011111010100111011 .
1/
#183
0/
#184
b00000000000000000000010010110000 +
b00000000000000000000000000001010 ,
b00000110101011011111010100111011 -
b11000110011011010100110101011000 .
1/
b0010 2
b0010 5
b00000000000000000000001010111100 7
#185
0/
#186
b00000000000000000000000000001001 ,
b11000110011011010100110101011000 -
b00000110101011011111010100111011 .
1/
b0000 2
b0000 5
b00000000000000000000010010110000 7
#187
0/
#188
b00000000000000000000000000001000 ,
b00000110101011011111010100111011 -
b11000110011011010100110101011000 .
1/
#189
0/
#190
b00000000000000000000000000000111 ,
b11000110011011010100110101011000 -
b00000110101011011111010100111011 .
1/
#191
0/
#192
b00000000000000000000001010111100 +
b00000000000000000000000000001010 ,
b00000110101011011111010100111011 -
b11000110011011010100110101011000 .
1/
b0010 2
b0011 4
b0010 5
b00000000000000000000000011001000 7
#193
0/
#194
b00000000000000000000000000001001 ,
b11000110011011010100110101011000 -
b00000110101011011111010100111011 .
1/
b0000 2
b0000 5
b00000000000000000000001010111100 7
#195
0/
#196
b00000000000000000000000000001000 ,
b00000110101011011111010100111011 -
b11000110011011010100110101011000 .
1/
#197
0/
#198
b00000000000000000000000000000111 ,
b11000110011011010100110101011000 -
b00000110101011011111010100111011 .
1/
#199
0/
#200
b00000000000000000000000011001000 +
b00000000000000000000000000001010 ,
b00000110101011011111010100111011 -
b11000110011011010100110101011000 .
1/
b0010 2
b0000 4
b00000000000000000000000011001000 7
#201
0/
#202
b00000000000000000000000000001001 ,
b11000110011011010100110101011000 -
b00000110101011011111010100111011 .
1/
b0000 2
#203
0/
#204
b00000000000000000000000000001000 ,
b00000110101011011111010100111011 -
b11000110011011010100110101011000 .
1/
#205
0/
#206
b00000000000000000000000000000111 ,
b11000110011011010100110101011000 -
b00000110101011011111010100111011 .
1/
#207
0/
#208
b00000000000000000000000100101100 +
b00000000000000000000000000001010 ,
b00000110101011011111010100111011 -
b11000110011011010100110101011000 .
1/
b001 1
b00000000000000000000000110010000 7
b00000000000000000000000001100100 8
#209
0/
#210
b00000000000000000000000000001001 ,
b11000110011011010100110101011000 -
b00000110101011011111010100111011 .
1/
b000 1
b00000000000000000000000100101100 7
b00000000000000000000000000000000 8
#211
0/
#212
b00000000000000000000000110010000 +
b00000000000000000000000000001010 ,
b00000110101011011111010100111011 -
b11000110011011010100110101011000 .
1/
b001 1
b0001 4
b00000000000000000000000111110100 7
b00000000000000000000000001100100 8
#213
0/
#214
b00000000000000000000000000001001 ,
b11000110011011010100110101011000 -
b00000110101011011111010100111011 .
1/
b000 1
b00000000000000000000000110010000 7
b00000000000000000000000000000000 8
#215
0/
#216
b00000000000000000000010101111000 +
b00000000000000000000000000001010 ,
b00000110101011011111010100111011 -
b11000110011011010100110101011000 .
1/
b100 1
b0111 4
b00000000000000000000100101100000 7
b00000000000000000000001111101000 8
#217
0/
#218
b00000000000000000000000000001001 ,
b11000110011011010100110101011000 -
b00000110101011011111010100111011 .
1/
b000 1
b00000000000000000000010101111000 7
b00000000000000000000000000000000 8
#219
0/
#220
b00000000000000000000100101100000 +
b00000000000000000000000000001010 ,
b00000110101011011111010100111011 -
b11000110011011010100110101011000 .
1/
b100 1
b1111 4
b00000000000000000000110101001000 7
b00000000000000000000001111101000 8
#221
0/
#222
b00000000000000000000000000001001 ,
b11000110011011010100110101011000 -
b00000110101011011111010100111011 .
1/
b000 1
b00000000000000000000100101100000 7
b00000000000000000000000000000000 8
#223
0/
#224
b00000000000000000000110101001000 +
b00000000000000000000000000001010 ,
b00000110101011011111010100111011 -
b11000110011011010100110101011000 .
1/
b100 1
b00000000000000000001000100110000 7
b00000000000000000000001111101000 8
#225
0/
#226
b00000000000000000000000000001001 ,
b11000110011011010100110101011000 -
b00000110101011011111010100111011 .
1/
b000 1
b00000000000000000000110101001000 7
b00000000000000000000000000000000 8
#227
0/
#228
b00000000000000000000100101100000 +
b00000000000000000000000000001010 ,
b00000110101011011111010100111011 -
b11000110011011010100110101011000 .
1/
b0100 2
b0100 5
b00000000000000000000010101111000 7
#229
0/
#230
b00000000000000000000000000001001 ,
b11000110011011010100110101011000 -
b00000110101011011111010100111011 .
1/
b0000 2
b0000 5
b00000000000000000000100101100000 7
#231
0/
#232
b00000000000000000000000000001000 ,
b00000110101011011111010100111011 -
b11000110011011010100110101011000 .
1/
#233
0/
#234
b00000000000000000000000000000111 ,
b11000110011011010100110101011000 -
b00000110101011011111010100111011 .
1/
#235
0/
#236
b00000000000000000000010101111000 +
b00000000000000000000000000001010 ,
b00000110101011011111010100111011 -
b11000110011011010100110101011000 .
1/
b0100 2
b0111 4
b0100 5
b00000000000000000000000110010000 7
#237
0/
#238
b00000000000000000000000000001001 ,
b11000110011011010100110101011000 -
b00000110101011011111010100111011 .
1/
b0000 2
b0000 5
b00000000000000000000010101111000 7
#239
0/
#240
b00000000000000000000000000001000 ,
b00000110101011011111010100111011 -
b11000110011011010100110101011000 .
1/
#241
0/
#242
b00000000000000000000000000000111 ,
b11000110011011010100110101011000 -
b00000110101011011111010100111011 .
1/
#243
0/
